{"name":"build-javascript","namedChunkGroups":{"polyfill":{"name":"polyfill","assets":[{"name":"webpack-runtime-4adc571b5198a9bda683.js","size":5240},{"name":"polyfill-59a98be205eb181a1051.js","size":85850}],"filteredAssets":0,"assetsSize":91090,"filteredAuxiliaryAssets":2,"auxiliaryAssetsSize":228704},"app":{"name":"app","assets":[{"name":"webpack-runtime-4adc571b5198a9bda683.js","size":5240},{"name":"framework-2eedc83b81eb3521280f.js","size":129763},{"name":"app-7369818dacf0ed6cee59.js","size":70713}],"filteredAssets":0,"assetsSize":205716,"filteredAuxiliaryAssets":3,"auxiliaryAssetsSize":664363},"component---src-pages-404-js":{"name":"component---src-pages-404-js","assets":[{"name":"styles.49e2aa6e969d1e5e4613.css","size":21818},{"name":"commons-bb7d37407a468727d521.js","size":399959},{"name":"db80b507951befab878d85bf25d3bc8f54f25455-76fee945623dd248e3e2.js","size":15797},{"name":"component---src-pages-404-js-2113ff03c79564ac64ac.js","size":473}],"filteredAssets":0,"assetsSize":438047,"filteredAuxiliaryAssets":5,"auxiliaryAssetsSize":1577755},"component---src-pages-index-tsx":{"name":"component---src-pages-index-tsx","assets":[{"name":"styles.49e2aa6e969d1e5e4613.css","size":21818},{"name":"commons-bb7d37407a468727d521.js","size":399959},{"name":"component---src-pages-index-tsx-3828742bfac79920a227.js","size":716}],"filteredAssets":0,"assetsSize":422493,"filteredAuxiliaryAssets":4,"auxiliaryAssetsSize":1512365},"component---src-templates-[locale]-tsx":{"name":"component---src-templates-[locale]-tsx","assets":[{"name":"styles.49e2aa6e969d1e5e4613.css","size":21818},{"name":"commons-bb7d37407a468727d521.js","size":399959},{"name":"db80b507951befab878d85bf25d3bc8f54f25455-76fee945623dd248e3e2.js","size":15797},{"name":"component---src-templates-[locale]-tsx-8994e05cb9f7053219c2.js","size":258504}],"filteredAssets":0,"assetsSize":696078,"filteredAuxiliaryAssets":5,"auxiliaryAssetsSize":2686397}},"assetsByChunkName":{"polyfill":["webpack-runtime-4adc571b5198a9bda683.js","polyfill-59a98be205eb181a1051.js"],"app":["webpack-runtime-4adc571b5198a9bda683.js","framework-2eedc83b81eb3521280f.js","app-7369818dacf0ed6cee59.js"],"component---src-pages-404-js":["styles.49e2aa6e969d1e5e4613.css","commons-bb7d37407a468727d521.js","db80b507951befab878d85bf25d3bc8f54f25455-76fee945623dd248e3e2.js","component---src-pages-404-js-2113ff03c79564ac64ac.js"],"component---src-pages-index-tsx":["styles.49e2aa6e969d1e5e4613.css","commons-bb7d37407a468727d521.js","component---src-pages-index-tsx-3828742bfac79920a227.js"],"component---src-templates-[locale]-tsx":["styles.49e2aa6e969d1e5e4613.css","commons-bb7d37407a468727d521.js","db80b507951befab878d85bf25d3bc8f54f25455-76fee945623dd248e3e2.js","component---src-templates-[locale]-tsx-8994e05cb9f7053219c2.js"]},"childAssetsByChunkName":{}}